{
  "groups": [
    {
      "name": "energy.url",
      "type": "com.enercomn.properties.GeneralProperties",
      "sourceType": "com.enercomn.properties.GeneralProperties"
    }
  ],
  "properties": [
    {
      "name": "energy.url.enterprise-code",
      "type": "java.lang.String",
      "sourceType": "com.enercomn.properties.GeneralProperties"
    },
    {
      "name": "energy.url.region",
      "type": "java.lang.String",
      "sourceType": "com.enercomn.properties.GeneralProperties"
    },
    {
      "name": "energy.url.register-url",
      "type": "java.lang.String",
      "sourceType": "com.enercomn.properties.GeneralProperties"
    },
    {
      "name": "energy.url.upload-energy-url",
      "type": "java.lang.String",
      "sourceType": "com.enercomn.properties.GeneralProperties"
    }
  ],
  "hints": []
}